spxr/__init__.py
spxr/ml.py
spxr-0.1.15.dist-info/LICENSE
spxr-0.1.15.dist-info/METADATA
spxr-0.1.15.dist-info/WHEEL
spxr-0.1.15.dist-info/top_level.txt
spxr-0.1.15.dist-info/RECORD
