Metadata-Version: 2.1
Name: spxr
Version: 0.1.15
Summary: Custom functions for repetitive tasks
Home-page: https://github.com/AregSP/spxr
Author: Areg Sargsyan
Author-email: quant0027@gmail.com
Classifier: Programming Language :: Python :: 3
Classifier: License :: OSI Approved :: MIT License
Classifier: Operating System :: OS Independent
Requires-Python: >=3.6
License-File: LICENSE
